polstats/__init__.py
polstats-0.1.0.dist-info/METADATA
polstats-0.1.0.dist-info/WHEEL
polstats-0.1.0.dist-info/top_level.txt
polstats-0.1.0.dist-info/RECORD
